mas_ai/__init__.py
mas_ai/AgentManager/AgentManager.py
mas_ai/AgentManager/__init__.py
mas_ai/Agents/__init__.py
mas_ai/Agents/singular_agent.py
mas_ai/GenerativeModel/__init__.py
mas_ai/GenerativeModel/generativeModels.py
mas_ai/GenerativeModel/baseGenerativeModel/basegenerativeModel.py
mas_ai/MultiAgents/MultiAgent.py
mas_ai/MultiAgents/__init__.py
mas_ai/OMAN/__init__.py
mas_ai/OMAN/oman.py
mas_ai/Tools/__init__.py
mas_ai/Tools/calendarTools.py
mas_ai/Tools/emailTools.py
mas_ai/Tools/mathTools.py
mas_ai/Tools/searchTools.py
mas_ai/Tools/visiontools.py
mas_ai/Tools/PARSERs/json_parser.py
mas_ai/Tools/logging_setup/logger.py
mas_ai/Tools/utilities/tokenGenerationTool.py
mas_ai/prompts/prompt_templates.py
mas_ai/pydanticModels/AnswerModel.py
mas_ai/pydanticModels/omanModel.py
mas_ai/pydanticModels/supervisorModels.py
multi_agent_system_ai-0.1.1.dist-info/LICENSE
multi_agent_system_ai-0.1.1.dist-info/METADATA
multi_agent_system_ai-0.1.1.dist-info/WHEEL
multi_agent_system_ai-0.1.1.dist-info/top_level.txt
multi_agent_system_ai-0.1.1.dist-info/RECORD
