Metadata-Version: 2.2
Name: multi_agent_system_ai
Version: 0.1.1
Summary: Multi-Agent System Framework for AI Agents built on LangGraph
Author-email: PILER <mrpolymathematica@gmail.com>
Requires-Python: >=3.9
License-File: LICENSE
Requires-Dist: langgraph>=0.2.67
Requires-Dist: langchain==0.3.15
Requires-Dist: langchain-community==0.3.15
Requires-Dist: langchain-core==0.3.31
Requires-Dist: pydantic>=2.0
Requires-Dist: python-dotenv
Requires-Dist: tqdm
Requires-Dist: requests
Requires-Dist: anthropic
Requires-Dist: openai
Requires-Dist: google-generativeai==0.8.4
Requires-Dist: langchain-groq==0.2.3
Requires-Dist: langchain-openai==0.3.2
Requires-Dist: langchain-text-splitters==0.3.5
Requires-Dist: langsmith
Requires-Dist: beautifulsoup4
Requires-Dist: arxiv
Requires-Dist: wikipedia
Requires-Dist: duckduckgo-search
Requires-Dist: psycopg2
Requires-Dist: tokenizers
Provides-Extra: tools
